{
    "generated_at": "2026-07-09T13:53:26Z",
    "collector": "Technical Collector",
    "agent_input_for": "Technical Agent",
    "data_source": "Yahoo Finance via yfinance",
    "note": "This collector automates EMA, momentum, and support/resistance candidate data. Manual chart trendlines and annotated screenshots are not automated yet.",
    "instruments": {
        "SPX": {
            "symbol": "SPX",
            "yahoo_ticker": "^GSPC",
            "name": "S&P 500 Index",
            "latest_trading_date": "2026-07-09",
            "last_close": 7516.22,
            "weekly_change_pct": 0.44,
            "ema_8": 7486.58,
            "ema_21": 7459.96,
            "price_vs_8ema": "above",
            "ema_8_vs_21ema": "above",
            "distance_from_8ema": 29.64,
            "distance_from_21ema": 56.26,
            "ema_gap": 26.62,
            "ema_condition": "Zone 1 Bullish",
            "recent_20d_high": 7577.92,
            "recent_20d_low": 7257.33,
            "resistance_candidate": 7577.92,
            "support_candidate": 7257.33,
            "technical_bias": "Bullish",
            "history_file": "technical/history/SPX.json"
        },
        "NDX": {
            "symbol": "NDX",
            "yahoo_ticker": "^NDX",
            "name": "Nasdaq 100 Index",
            "latest_trading_date": "2026-07-09",
            "last_close": 29684.98,
            "weekly_change_pct": -0.42,
            "ema_8": 29533.71,
            "ema_21": 29566.21,
            "price_vs_8ema": "above",
            "ema_8_vs_21ema": "below",
            "distance_from_8ema": 151.27,
            "distance_from_21ema": 118.77,
            "ema_gap": -32.5,
            "ema_condition": "Mixed / Neutral",
            "recent_20d_high": 30642.57,
            "recent_20d_low": 28462.92,
            "resistance_candidate": 30642.57,
            "support_candidate": 28462.92,
            "technical_bias": "Neutral",
            "history_file": "technical/history/NDX.json"
        },
        "IWM": {
            "symbol": "IWM",
            "yahoo_ticker": "IWM",
            "name": "Russell 2000 ETF Proxy",
            "latest_trading_date": "2026-07-09",
            "last_close": 296.57,
            "weekly_change_pct": -0.92,
            "ema_8": 296.71,
            "ema_21": 294.59,
            "price_vs_8ema": "below",
            "ema_8_vs_21ema": "above",
            "distance_from_8ema": -0.14,
            "distance_from_21ema": 1.98,
            "ema_gap": 2.12,
            "ema_condition": "Zone 2 Pullback",
            "recent_20d_high": 302.72,
            "recent_20d_low": 281.09,
            "resistance_candidate": 302.72,
            "support_candidate": 281.09,
            "technical_bias": "Neutral",
            "history_file": "technical/history/IWM.json"
        }
    }
}